{
  "feedback": "请详细解释Phase 1; 检索准确率 目前以都达到100%了",
  "action": "你说得对！让我更新数据：\n\n## ✅ 检索准确率已达标\n\n| Benchmark | 分数 | 目标 | 状态 |\n|-----------|------|------|------|\n| LongMemEval | **100%** | ≥75% | ✅ |\n| LoCoMo | **100%** | ≥80% | ✅ |\n| ConvoMem | **100%** | ≥75% | ✅ |\n\n---\n\n### 更新后的 Phase 1 完成度\n\n| # | 承诺项 | 状态 |\n|---|--------|------|\n| 1 | 持久化存储与智能检索 | ✅ 100% |\n| 2 | 跨时间,跨上下文的关联记忆 | ✅ 90% |\n| 3 | 基于模式的预测性召回 | ⚠️ 30% |\n| 4 | 多模态支持 | ⚠️ 40% |\n| 5 | 10万+ 用户 | ❌ 0% |\n| ",
  "context": "",
  "reward": 0,
  "confidence": 0.5,
  "pattern_matched": null,
  "hints": [],
  "timestamp": "2026-05-02T00:11:03.818485"
}